core/App.py
core/BotLogger.py
core/Locust.py
core/LocustSettings.py
core/Swarm.py
core/__init__.py
locust_swarm_wrapper_lib-0.0.1.dist-info/METADATA
locust_swarm_wrapper_lib-0.0.1.dist-info/WHEEL
locust_swarm_wrapper_lib-0.0.1.dist-info/top_level.txt
locust_swarm_wrapper_lib-0.0.1.dist-info/RECORD
