Metadata-Version: 2.4
Name: locust_swarm_wrapper_lib
Version: 0.0.1
Summary: App for loading testing, wrapper for locust library
Author: Cupcake_wrld
Author-email: evilprog@yandex.ru
Keywords: files small console load_testing
Classifier: Programming Language :: Python :: 3.12
Classifier: Operating System :: OS Independent
Requires-Python: >=3.12
Dynamic: author
Dynamic: author-email
Dynamic: classifier
Dynamic: description
Dynamic: description-content-type
Dynamic: keywords
Dynamic: requires-python
Dynamic: summary
